sovpy/__init__.py
sovpy-0.1.0.dist-info/WHEEL
sovpy-0.1.0.dist-info/METADATA
sovpy-0.1.0.dist-info/RECORD
